setup.cfg
setup.py
pogopowerupcost/__init__.py
pogopowerupcost/pogopowerupcost.py
pogopowerupcost.egg-info/PKG-INFO
pogopowerupcost.egg-info/SOURCES.txt
pogopowerupcost.egg-info/dependency_links.txt
pogopowerupcost.egg-info/top_level.txt