Metadata-Version: 1.1
Name: pogopowerupcost
Version: 1.0.2
Summary: Easily calculate how much stardust and candy it takes to power-up a Pokémon from level `a` to level `b` in Pokémon GO.
Home-page: https://github.com/mathiasbynens/pogopowerupcost
Author: Mathias Bynens
Author-email: mathias@qiwi.be
License: MIT
Download-URL: https://github.com/mathiasbynens/pogopowerupcost/tarball/v1.0.2
Keywords: pogo,pokemon go,stardust,candy
Platform: UNKNOWN
Classifier: Development Status :: 5 - Production/Stable
Classifier: Intended Audience :: Developers
Classifier: License :: OSI Approved :: MIT License
Classifier: Operating System :: MacOS :: MacOS X
Classifier: Operating System :: Microsoft :: Windows
Classifier: Operating System :: POSIX :: Linux
Classifier: Operating System :: POSIX
Classifier: Programming Language :: Python :: 2.6
Classifier: Programming Language :: Python :: 2.7
Classifier: Programming Language :: Python :: 3.3
Classifier: Programming Language :: Python :: 3.4
Classifier: Programming Language :: Python :: 3.5
Classifier: Programming Language :: Python :: Implementation :: PyPy
Classifier: Topic :: Software Development :: Libraries
